{"categories": [{"name": "receiving", "displayName": "Receiving", "count": 6}, {"name": "rushing", "displayName": "Rushing", "count": 5}, {"name": "fumbles", "displayName": "Fumbles", "count": 4}], "filters": [{"displayName": "League", "name": "league", "value": "nfl", "options": [{"value": "college-football", "displayValue": "NCAA - Football", "shortDisplayName": "NCAAF"}, {"value": "nfl", "displayValue": "National Football League", "shortDisplayName": "NFL"}]}, {"displayName": "Season", "name": "season", "value": "2016", "options": [{"value": "2025", "displayValue": "2025"}, {"value": "2024", "displayValue": "2024"}, {"value": "2023", "displayValue": "2023"}, {"value": "2022", "displayValue": "2022"}, {"value": "2021", "displayValue": "2021"}, {"value": "2020", "displayValue": "2020"}, {"value": "2019", "displayValue": "2019"}, {"value": "2018", "displayValue": "2018"}, {"value": "2017", "displayValue": "2017"}, {"value": "2016", "displayValue": "2016"}, {"value": "2015", "displayValue": "2015"}, {"value": "2014", "displayValue": "2014"}, {"value": "2013", "displayValue": "2013"}]}], "labels": ["REC", "TGTS", "YDS", "AVG", "TD", "LNG", "CAR", "YDS", "AVG", "LNG", "TD", "FUM", "LST", "FF", "KB"], "names": ["receptions", "receivingTargets", "receivingYards", "yardsPerReception", "receivingTouchdowns", "longReception", "rushingAttempts", "rushingYards", "yardsPerRushAttempt", "longRushing", "rushingTouchdowns", "fumbles", "fumblesLost", "fumblesForced", "kicksBlocked"], "displayNames": ["Receptions", "Receiving Targets", "Receiving Yards", "Yards Per Reception", "Receiving Touchdowns", "Long Reception", "Rushing Attempts", "Rushing Yards", "Yards Per Rush Attempt", "Long Rushing", "Rushing Touchdowns", "Fumbles", "Fumbles Lost", "Forced Fumbles", "Kicks Blocked"], "events": {"400874570": {"id": "400874570", "links": [{"language": "en", "rel": ["summary", "desktop", "event"], "href": "https://www.espn.com/nfl/game/_/gameId/400874570/chargers-chiefs", "text": "Gamecast", "shortText": "Summary", "isExternal": false, "isPremium": false}, {"language": "en", "rel": ["summary", "sportscenter", "app", "event"], "href": "sportscenter://x-callback-url/showGame?sportName=football&leagueAbbrev=nfl&gameId=400874570", "text": "Gamecast", "shortText": "Summary", "isExternal": false, "isPremium": false}, {"language": "en", "rel": ["now", "desktop", "event"], "href": "https://www.espn.com/nfl/game/_/gameId/400874570", "text": "Now", "shortText": "Now", "isExternal": false, "isPremium": false}, {"language": "en", "rel": ["teamstats", "desktop", "event"], "href": "https://www.espn.com/nfl/matchup?gameId=400874570", "text": "Team Stats", "shortText": "Team Stats", "isExternal": false, "isPremium": false}, {"language": "en", "rel": ["boxscore", "desktop", "event"], "href": "https://www.espn.com/nfl/boxscore/_/gameId/400874570", "text": "Box Score", "shortText": "Box Score", "isExternal": false, "isPremium": false}, {"language": "en", "rel": ["boxscore", "sportscenter", "app", "event"], "href": "sportscenter://x-callback-url/showGame?sportName=football&leagueAbbrev=nfl&gameId=400874570", "text": "Box Score", "shortText": "Box Score", "isExternal": false, "isPremium": false}, {"language": "en", "rel": ["gamecast", "desktop", "event"], "href": "https://www.espn.com/nfl/game/_/gameId/400874570", "text": "Gamecast", "shortText": "Gamecast", "isExternal": false, "isPremium": false}, {"language": "en", "rel": ["gamecast", "mobile", "event"], "href": "http://m.espn.com/nfl/gamecast?gameId=400874570&action=summary", "text": "Gamecast", "shortText": "Gamecast", "isExternal": false, "isPremium": false}, {"language": "en", "rel": ["gamecast", "sportscenter", "app", "event"], "href": "sportscenter://x-callback-url/showGame?sportName=football&leagueAbbrev=nfl&gameId=400874570", "text": "Gamecast", "shortText": "Gamecast", "isExternal": false, "isPremium": false}, {"language": "en", "rel": ["recap", "desktop", "event"], "href": "https://www.espn.com/nfl/recap?gameId=400874570", "text": "Recap", "shortText": "Recap", "isExternal": false, "isPremium": false}, {"language": "en", "rel": ["pbp", "desktop", "event"], "href": "https://www.espn.com/nfl/playbyplay/_/gameId/400874570", "text": "Play-by-Play", "shortText": "Play-by-Play", "isExternal": false, "isPremium": false}, {"language": "en", "rel": ["videos", "desktop", "event"], "href": "https://www.espn.com/nfl/video?gameId=400874570", "text": "Videos", "shortText": "Videos", "isExternal": false, "isPremium": false}, {"language": "en", "rel": ["odds", "desktop", "event"], "href": "https://www.espn.com/nfl/odds/_/gameId/400874570", "text": "Odds", "shortText": "Odds", "isExternal": false, "isPremium": false}, {"language": "en", "rel": ["odds", "mobile", "event"], "href": "https://m.espn.com/nfl/odds/_/gameId/400874570", "text": "Odds", "shortText": "Odds", "isExternal": false, "isPremium": false}], "week": 1, "atVs": "@", "gameDate": "2016-09-11T17:00:00.000+00:00", "score": "33-27 OT", "homeTeamId": "12", "awayTeamId": "24", "homeTeamScore": "33", "awayTeamScore": "27", "gameResult": "L", "opponent": {"id": "12", "uid": "s:20~l:28~t:12", "displayName": "Kansas City Chiefs", "abbreviation": "KC", "links": [{"language": "en", "rel": ["clubhouse", "desktop", "team"], "href": "https://www.espn.com/nfl/team/_/name/kc/kansas-city-chiefs", "text": "Clubhouse", "shortText": "Clubhouse", "isExternal": false, "isPremium": false}, {"language": "en", "rel": ["roster", "desktop", "team"], "href": "https://www.espn.com/nfl/team/roster/_/name/kc/kansas-city-chiefs", "text": "Roster", "shortText": "Roster", "isExternal": false, "isPremium": false}, {"language": "en", "rel": ["stats", "desktop", "team"], "href": "https://www.espn.com/nfl/team/stats/_/name/kc/kansas-city-chiefs", "text": "Statistics", "shortText": "Statistics", "isExternal": false, "isPremium": false}, {"language": "en", "rel": ["schedule", "desktop", "team"], "href": "https://www.espn.com/nfl/team/schedule/_/name/kc", "text": "Schedule", "shortText": "Schedule", "isExternal": false, "isPremium": false}, {"language": "en", "rel": ["photos", "desktop", "team"], "href": "https://www.espn.com/nfl/team/photos/_/name/kc", "text": "photos", "shortText": "photos", "isExternal": false, "isPremium": false}, {"language": "en", "rel": ["tickets", "desktop", "team"], "href": "https://www.vividseats.com/kansas-city-chiefs-tickets--sports-nfl-football/performer/427?wsUser=717", "text": "Tickets", "shortText": "Tickets", "isExternal": true, "isPremium": false}, {"language": "en", "rel": ["draftpicks", "desktop", "team"], "href": "https://www.espn.com/nfl/draft/teams/_/name/kc/kansas-city-chiefs", "text": "Draft Picks", "shortText": "Draft Picks", "isExternal": false, "isPremium": true}, {"language": "en", "rel": ["transactions", "desktop", "team"], "href": "https://www.espn.com/nfl/team/transactions/_/name/kc", "text": "Transactions", "shortText": "Transactions", "isExternal": false, "isPremium": false}, {"language": "en", "rel": ["injuries", "desktop", "team"], "href": "https://www.espn.com/nfl/team/injuries/_/name/kc", "text": "Injuries", "shortText": "Injuries", "isExternal": false, "isPremium": false}, {"language": "en", "rel": ["depthchart", "desktop", "team"], "href": "https://www.espn.com/nfl/team/depth/_/name/kc", "text": "Depth Chart", "shortText": "Depth Chart", "isExternal": false, "isPremium": false}], "logo": "https://a.espncdn.com/i/teamlogos/nfl/500/kc.png"}, "leagueName": "National Football League", "leagueAbbreviation": "NFL", "leagueShortName": "NFL", "team": {"id": "24", "uid": "s:20~l:28~t:24", "abbreviation": "SD", "links": [{"language": "en", "rel": ["clubhouse", "desktop", "team"], "href": "https://www.espn.com/nfl/team/_/name/lac/los-angeles-chargers", "text": "Clubhouse", "shortText": "Clubhouse", "isExternal": false, "isPremium": false}, {"language": "en", "rel": ["roster", "desktop", "team"], "href": "https://www.espn.com/nfl/team/roster/_/name/lac/los-angeles-chargers", "text": "Roster", "shortText": "Roster", "isExternal": false, "isPremium": false}, {"language": "en", "rel": ["stats", "desktop", "team"], "href": "https://www.espn.com/nfl/team/stats/_/name/lac/los-angeles-chargers", "text": "Statistics", "shortText": "Statistics", "isExternal": false, "isPremium": false}, {"language": "en", "rel": ["schedule", "desktop", "team"], "href": "https://www.espn.com/nfl/team/schedule/_/name/lac", "text": "Schedule", "shortText": "Schedule", "isExternal": false, "isPremium": false}, {"language": "en", "rel": ["photos", "desktop", "team"], "href": "https://www.espn.com/nfl/team/photos/_/name/lac", "text": "photos", "shortText": "photos", "isExternal": false, "isPremium": false}, {"language": "en", "rel": ["tickets", "desktop", "team"], "href": "https://www.vividseats.com/los-angeles-chargers-tickets--sports-nfl-football/performer/755?wsUser=717", "text": "Tickets", "shortText": "Tickets", "isExternal": true, "isPremium": false}, {"language": "en", "rel": ["draftpicks", "desktop", "team"], "href": "https://www.espn.com/nfl/draft/teams/_/name/lac/los-angeles-chargers", "text": "Draft Picks", "shortText": "Draft Picks", "isExternal": false, "isPremium": true}, {"language": "en", "rel": ["transactions", "desktop", "team"], "href": "https://www.espn.com/nfl/team/transactions/_/name/lac", "text": "Transactions", "shortText": "Transactions", "isExternal": false, "isPremium": false}, {"language": "en", "rel": ["injuries", "desktop", "team"], "href": "https://www.espn.com/nfl/team/injuries/_/name/lac", "text": "Injuries", "shortText": "Injuries", "isExternal": false, "isPremium": false}, {"language": "en", "rel": ["depthchart", "desktop", "team"], "href": "https://www.espn.com/nfl/team/depth/_/name/lac", "text": "Depth Chart", "shortText": "Depth Chart", "isExternal": false, "isPremium": false}], "logo": "https://a.espncdn.com/guid/84caf62b-c753-71ea-a787-44fd224a4294/logos/default.png", "isAllStar": false}}}, "seasonTypes": [{"displayName": "2016 Regular Season", "displayTeam": "SD", "categories": [{"displayName": "Regular Season Stats", "type": "event", "splitType": "2", "events": [{"eventId": "400874570", "stats": ["6", "7", "63", "10.5", "0", "15", "0", "0", "0.0", "0", "0", "0", "0", "0", "0"]}], "totals": ["6", "7", "63", "10.5", "0", "15", "0", "0", "0.0", "0", "0", "0", "0", "-", "-"]}], "summary": {"displayName": "Regular Season Stats", "stats": [{"displayName": "Totals", "stats": ["6", "7", "63", "10.5", "0", "15", "0", "0", "0.0", "0", "0", "0", "0", "-", "-"], "type": "total"}]}}], "glossary": [{"abbreviation": "AVG", "displayName": "Yards Per Reception"}, {"abbreviation": "CAR", "displayName": "Rushing Attempts"}, {"abbreviation": "FF", "displayName": "Forced Fumbles"}, {"abbreviation": "FUM", "displayName": "Fumbles"}, {"abbreviation": "KB", "displayName": "Kicks Blocked"}, {"abbreviation": "LNG", "displayName": "Long Reception"}, {"abbreviation": "LST", "displayName": "Fumbles Lost"}, {"abbreviation": "REC", "displayName": "Receptions"}, {"abbreviation": "TD", "displayName": "Receiving Touchdowns"}, {"abbreviation": "TGTS", "displayName": "Receiving Targets"}, {"abbreviation": "YDS", "displayName": "Receiving Yards"}]}